jupyterlab_bxplorer_v2/__init__.py
jupyterlab_bxplorer_v2/_version.py
jupyterlab_bxplorer_v2/config_handler.py
jupyterlab_bxplorer_v2/download_history.py
jupyterlab_bxplorer_v2/download_history_handler.py
jupyterlab_bxplorer_v2/favorites.py
jupyterlab_bxplorer_v2/favorites_handler.py
jupyterlab_bxplorer_v2/file_manager_handler.py
jupyterlab_bxplorer_v2/handlers.py
jupyterlab_bxplorer_v2/labextension/build_log.json
jupyterlab_bxplorer_v2/labextension/package.json
jupyterlab_bxplorer_v2/labextension/schemas/jupyterlab-bxplorer-v2/package.json.orig
jupyterlab_bxplorer_v2/labextension/schemas/jupyterlab-bxplorer-v2/plugin.json
jupyterlab_bxplorer_v2/labextension/static/1e673ba8589654794d2a.woff2
jupyterlab_bxplorer_v2/labextension/static/35dca8a7145a17c8d130.woff2
jupyterlab_bxplorer_v2/labextension/static/8265f64786397d6b832d.woff2
jupyterlab_bxplorer_v2/labextension/static/c948f1263341699b3c1e.woff2
jupyterlab_bxplorer_v2/labextension/static/lib_index_js.844a485f5f4b5a24633f.js
jupyterlab_bxplorer_v2/labextension/static/lib_index_js.844a485f5f4b5a24633f.js.map
jupyterlab_bxplorer_v2/labextension/static/node_modules_emotion_use-insertion-effect-with-fallbacks_dist_emotion-use-insertion-effect-wi-3c9bb40.82f12c24a3f7df18ba8e.js
jupyterlab_bxplorer_v2/labextension/static/node_modules_emotion_use-insertion-effect-with-fallbacks_dist_emotion-use-insertion-effect-wi-3c9bb40.82f12c24a3f7df18ba8e.js.map
jupyterlab_bxplorer_v2/labextension/static/node_modules_emotion_use-insertion-effect-with-fallbacks_dist_emotion-use-insertion-effect-wi-3c9bb41.8d1266da0c2350e8dc09.js
jupyterlab_bxplorer_v2/labextension/static/node_modules_emotion_use-insertion-effect-with-fallbacks_dist_emotion-use-insertion-effect-wi-3c9bb41.8d1266da0c2350e8dc09.js.map
jupyterlab_bxplorer_v2/labextension/static/remoteEntry.0262720a6ec9abd68399.js
jupyterlab_bxplorer_v2/labextension/static/remoteEntry.0262720a6ec9abd68399.js.map
jupyterlab_bxplorer_v2/labextension/static/style.js
jupyterlab_bxplorer_v2-0.2.25.dist-info/METADATA
jupyterlab_bxplorer_v2-0.2.25.dist-info/WHEEL
jupyterlab_bxplorer_v2-0.2.25.dist-info/licenses/LICENSE
jupyterlab_bxplorer_v2-0.2.25.dist-info/RECORD
