Metadata-Version: 2.4
Name: jupyterlab_bxplorer_v2
Version: 0.2.25
Summary: A JupyterLab extension that integrates a modern file management interface using Syncfusion's FileManager component. It enables seamless browsing, searching, and management of both public and private data buckets (e.g., AWS S3 buckets) directly within JupyterLab. Featuring multi-tab navigation, client-type filtering, and robust file operations, this extension enhances data accessibility and management in an intuitive environment.
Project-URL: Homepage, https://github.com/Navteca/jupyterlab-bxplorer-v2
Project-URL: Bug Tracker, https://github.com/Navteca/jupyterlab-bxplorer-v2/issues
Project-URL: Repository, https://github.com/Navteca/jupyterlab-bxplorer-v2.git
Author-email: Navteca LLC <info@navteca.com>
License: BSD 3-Clause License
License-File: LICENSE
Keywords: jupyter,jupyterlab,jupyterlab-extension
Classifier: Framework :: Jupyter
Classifier: Framework :: Jupyter :: JupyterLab
Classifier: Framework :: Jupyter :: JupyterLab :: 4
Classifier: Framework :: Jupyter :: JupyterLab :: Extensions
Classifier: Framework :: Jupyter :: JupyterLab :: Extensions :: Prebuilt
Classifier: License :: OSI Approved :: BSD License
Classifier: Programming Language :: Python
Classifier: Programming Language :: Python :: 3
Classifier: Programming Language :: Python :: 3.9
Classifier: Programming Language :: Python :: 3.10
Classifier: Programming Language :: Python :: 3.11
Classifier: Programming Language :: Python :: 3.12
Classifier: Programming Language :: Python :: 3.13
Requires-Python: >=3.9
Requires-Dist: asyncio
Requires-Dist: boto3
Requires-Dist: botocore
Requires-Dist: jupyter-server<3,>=2.4.0
Requires-Dist: sqlalchemy
Provides-Extra: test
Requires-Dist: coverage; extra == 'test'
Requires-Dist: pytest; extra == 'test'
Requires-Dist: pytest-asyncio; extra == 'test'
Requires-Dist: pytest-cov; extra == 'test'
Requires-Dist: pytest-jupyter[server]>=0.6.0; extra == 'test'
